iterm_file_handler/__init__.py
iterm_file_handler/__main__.py
iterm_file_handler/iterm_file_handler.py
iterm_file_handler-0.0.3.dist-info/LICENSE
iterm_file_handler-0.0.3.dist-info/METADATA
iterm_file_handler-0.0.3.dist-info/WHEEL
iterm_file_handler-0.0.3.dist-info/entry_points.txt
iterm_file_handler-0.0.3.dist-info/top_level.txt
iterm_file_handler-0.0.3.dist-info/RECORD
