Metadata-Version: 2.1
Name: iterm-file-handler
Version: 0.0.3
Summary: Handle default app for file in iterm
Home-page: https://github.com/pr4bh4sh/iterm-file-handler
Author: pr4bh4sh
License: UNKNOWN
Platform: UNKNOWN
